agent_reward_bench/__init__.py
agent_reward_bench/trajectories.py
agent_reward_bench/utils.py
agent_reward_bench/version.py
agent_reward_bench/benchmarks/__init__.py
agent_reward_bench/benchmarks/base.py
agent_reward_bench/data/annotations.csv
agent_reward_bench/data/assistantbench.csv
agent_reward_bench/data/complete_task_ids.csv
agent_reward_bench/data/splits.csv
agent_reward_bench/data/visualwebarena.csv
agent_reward_bench/data/visualwebarena.task_ids.json
agent_reward_bench/data/webarena.csv
agent_reward_bench/data/webarena.task_ids.json
agent_reward_bench/data/workarena.csv
agent_reward_bench/data/workarena_l2.task_ids.json
agent_reward_bench/eval/__init__.py
agent_reward_bench/eval/metrics.py
agent_reward_bench/eval/utils.py
agent_reward_bench/judge/__init__.py
agent_reward_bench/judge/args.py
agent_reward_bench/judge/defaults.py
agent_reward_bench/judge/utils.py
agent_reward_bench/judge/existing/__init__.py
agent_reward_bench/judge/existing/aer.py
agent_reward_bench/judge/existing/nnetnav.py
agent_reward_bench/modeling/__init__.py
agent_reward_bench-0.1.2.dist-info/METADATA
agent_reward_bench-0.1.2.dist-info/WHEEL
agent_reward_bench-0.1.2.dist-info/top_level.txt
agent_reward_bench-0.1.2.dist-info/RECORD
