Metadata-Version: 2.4
Name: agent-reward-bench
Version: 0.1.2
Summary: Official library for AgentRewardBench: Evaluating Automatic Evaluations of Web Agent Trajectories
Home-page: https://github.com/McGill-NLP/agent-reward-bench
Author: McGill NLP
Author-email: agent-reward-bench@googlegroups.com
Classifier: Programming Language :: Python :: 3
Requires-Python: >=3.10
Requires-Dist: browsergym
Requires-Dist: numpy
Requires-Dist: pandas
Requires-Dist: Pillow
Requires-Dist: tqdm
Provides-Extra: dev
Requires-Dist: black; extra == "dev"
Requires-Dist: wheel; extra == "dev"
Provides-Extra: extra
Requires-Dist: huggingface-hub; extra == "extra"
Requires-Dist: orjson; extra == "extra"
Provides-Extra: all
Requires-Dist: black; extra == "all"
Requires-Dist: wheel; extra == "all"
Requires-Dist: huggingface-hub; extra == "all"
Requires-Dist: orjson; extra == "all"
Dynamic: author
Dynamic: author-email
Dynamic: classifier
Dynamic: description
Dynamic: description-content-type
Dynamic: home-page
Dynamic: provides-extra
Dynamic: requires-dist
Dynamic: requires-python
Dynamic: summary
